{"summaries":[{"symbol":{"__symbol":0,"members":[]},"metadata":{"__symbolic":"class"},"type":{"summaryKind":2,"type":{"reference":{"__symbol":0,"members":[]},"diDeps":[],"lifecycleHooks":[]},"entryComponents":[{"componentType":{"__symbol":1,"members":[]},"componentFactory":{"__symbol":2,"members":[]}},{"componentType":{"__symbol":3,"members":[]},"componentFactory":{"__symbol":4,"members":[]}},{"componentType":{"__symbol":5,"members":[]},"componentFactory":{"__symbol":6,"members":[]}},{"componentType":{"__symbol":7,"members":[]},"componentFactory":{"__symbol":8,"members":[]}}],"providers":[{"provider":{"token":{"identifier":{"reference":{"__symbol":9,"members":[]}}},"useClass":null,"useValue":[{"path":"mcq/create/:moduleid","component":{"__symbol":1,"members":[]},"canActivate":[{"__symbol":10,"members":[]}]},{"path":"mcq/edit/:id/:version","component":{"__symbol":3,"members":[]},"canActivate":[{"__symbol":10,"members":[]}]},{"path":"mcq/view/:id","component":{"__symbol":5,"members":[]},"canActivate":[{"__symbol":10,"members":[]}]},{"path":"mcqs/view/:module/:rating/:generation/:original/:number","component":{"__symbol":7,"members":[]},"canActivate":[{"__symbol":10,"members":[]}]}],"useFactory":null,"useExisting":null,"multi":true},"module":{"reference":{"__symbol":0,"members":[]},"diDeps":[],"lifecycleHooks":[]}}],"modules":[{"reference":{"__symbol":11,"members":[]},"diDeps":[{"isAttribute":false,"isHost":false,"isSelf":false,"isSkipSelf":false,"isOptional":true,"token":{"identifier":{"reference":{"__symbol":12,"members":[]}}}},{"isAttribute":false,"isHost":false,"isSelf":false,"isSkipSelf":false,"isOptional":true,"token":{"identifier":{"reference":{"__symbol":13,"members":[]}}}}],"lifecycleHooks":[]},{"reference":{"__symbol":0,"members":[]},"diDeps":[],"lifecycleHooks":[]}],"exportedDirectives":[{"reference":{"__symbol":14,"members":[]}},{"reference":{"__symbol":15,"members":[]}},{"reference":{"__symbol":16,"members":[]}},{"reference":{"__symbol":17,"members":[]}}],"exportedPipes":[]}}],"symbols":[{"__symbol":0,"name":"McqRoutingModule","filePath":"/data/eike/data/Code/olm_client/src/app/mcq/mcq-routing.module.d.ts"},{"__symbol":1,"name":"McqCreateComponent","filePath":"/data/eike/data/Code/olm_client/src/app/mcq/mcq-create.component.d.ts"},{"__symbol":2,"name":"McqCreateComponentNgFactory","filePath":"/data/eike/data/Code/olm_client/src/app/mcq/mcq-create.component.ngfactory.d.ts"},{"__symbol":3,"name":"McqEditComponent","filePath":"/data/eike/data/Code/olm_client/src/app/mcq/mcq-edit.component.d.ts"},{"__symbol":4,"name":"McqEditComponentNgFactory","filePath":"/data/eike/data/Code/olm_client/src/app/mcq/mcq-edit.component.ngfactory.d.ts"},{"__symbol":5,"name":"McqViewComponent","filePath":"/data/eike/data/Code/olm_client/src/app/mcq/mcq-view.component.d.ts"},{"__symbol":6,"name":"McqViewComponentNgFactory","filePath":"/data/eike/data/Code/olm_client/src/app/mcq/mcq-view.component.ngfactory.d.ts"},{"__symbol":7,"name":"McqsViewComponent","filePath":"/data/eike/data/Code/olm_client/src/app/mcq/mcqs-view.component.d.ts"},{"__symbol":8,"name":"McqsViewComponentNgFactory","filePath":"/data/eike/data/Code/olm_client/src/app/mcq/mcqs-view.component.ngfactory.d.ts"},{"__symbol":9,"name":"ROUTES","filePath":"/data/eike/data/Code/olm_client/node_modules/@angular/router/router.d.ts"},{"__symbol":10,"name":"OlmService","filePath":"/data/eike/data/Code/olm_client/src/app/services/olm.service.d.ts"},{"__symbol":11,"name":"RouterModule","filePath":"/data/eike/data/Code/olm_client/node_modules/@angular/router/router.d.ts"},{"__symbol":12,"name":"ɵa","filePath":"/data/eike/data/Code/olm_client/node_modules/@angular/router/router.d.ts"},{"__symbol":13,"name":"Router","filePath":"/data/eike/data/Code/olm_client/node_modules/@angular/router/router.d.ts"},{"__symbol":14,"name":"RouterOutlet","filePath":"/data/eike/data/Code/olm_client/node_modules/@angular/router/router.d.ts"},{"__symbol":15,"name":"RouterLink","filePath":"/data/eike/data/Code/olm_client/node_modules/@angular/router/router.d.ts"},{"__symbol":16,"name":"RouterLinkWithHref","filePath":"/data/eike/data/Code/olm_client/node_modules/@angular/router/router.d.ts"},{"__symbol":17,"name":"RouterLinkActive","filePath":"/data/eike/data/Code/olm_client/node_modules/@angular/router/router.d.ts"}]}